llama_ocr/__init__.py
llama_ocr/cli.py
llama_ocr/llama_ocr.py
llama_ocr-0.2.0.dist-info/AUTHORS.rst
llama_ocr-0.2.0.dist-info/LICENSE
llama_ocr-0.2.0.dist-info/METADATA
llama_ocr-0.2.0.dist-info/WHEEL
llama_ocr-0.2.0.dist-info/top_level.txt
llama_ocr-0.2.0.dist-info/RECORD
