Metadata-Version: 2.1
Name: llama_ocr
Version: 0.2.0
Summary: OCR using LLAMA vision model, allowing configuring any OpenAI compliant endpoints and model names.
Author-email: Lyon Liang <ll_nwpu@qq.com>
Maintainer-email: Lyon Liang <ll_nwpu@qq.com>
License: MIT license
Project-URL: bugs, https://github.com/1WorldCapture/llama_ocr/issues
Project-URL: changelog, https://github.com/1WorldCapture/llama_ocr/blob/master/changelog.md
Project-URL: homepage, https://github.com/1WorldCapture/llama_ocr
License-File: LICENSE
License-File: AUTHORS.rst
Requires-Dist: typer
Requires-Dist: openai>=1.0.0
Requires-Dist: pillow>=10.0.0
Requires-Dist: python-dotenv>=1.0.0
Provides-Extra: dev
Requires-Dist: coverage; extra == "dev"
Requires-Dist: mypy; extra == "dev"
Requires-Dist: pytest; extra == "dev"
Requires-Dist: ruff; extra == "dev"
